MAJOR_1_1 = "short  45"
MINOR_1_1 = "short  3"
MAJOR_1_2 = "short  46"
MINOR_1_2 = "short  0"
MAJOR_1_3 = "short  47"
MINOR_1_3 = "short  0"
MAJOR_1_4 = "short  48"
MINOR_1_4 = "short  0"
MAJOR_1_5 = "short  49"
MINOR_1_5 = "short  0"
MAJOR = "short  45"
MINOR = "short  3"
MAX_SHORT = "int  65535"
MAX_BYTE = "int  255"
ACC_PUBLIC = "short  1"
ACC_PRIVATE = "short  2"
ACC_PROTECTED = "short  4"
ACC_STATIC = "short  8"
ACC_FINAL = "short  16"
ACC_SYNCHRONIZED = "short  32"
ACC_VOLATILE = "short  64"
ACC_BRIDGE = "short  64"
ACC_TRANSIENT = "short  128"
ACC_VARARGS = "short  128"
ACC_NATIVE = "short  256"
ACC_INTERFACE = "short  512"
ACC_ABSTRACT = "short  1024"
ACC_STRICT = "short  2048"
ACC_SYNTHETIC = "short  4096"
ACC_ANNOTATION = "short  8192"
ACC_ENUM = "short  16384"
ACC_SUPER = "short  32"
MAX_ACC_FLAG = "short  16384"
ACCESS_NAMES = "String[]  { \"public\", \"private\", \"protected\", \"static\", \"final\", \"synchronized\", \"volatile\", \"transient\", \"native\", \"interface\", \"abstract\", \"strictfp\", \"synthetic\", \"annotation\", \"enum\" }"
CONSTANT_Utf8 = "byte  1"
CONSTANT_Integer = "byte  3"
CONSTANT_Float = "byte  4"
CONSTANT_Long = "byte  5"
CONSTANT_Double = "byte  6"
CONSTANT_Class = "byte  7"
CONSTANT_Fieldref = "byte  9"
CONSTANT_String = "byte  8"
CONSTANT_Methodref = "byte  10"
CONSTANT_InterfaceMethodref = "byte  11"
CONSTANT_NameAndType = "byte  12"
CONSTANT_NAMES = "String[]  { \"\", \"CONSTANT_Utf8\", \"\", \"CONSTANT_Integer\", \"CONSTANT_Float\", \"CONSTANT_Long\", \"CONSTANT_Double\", \"CONSTANT_Class\", \"CONSTANT_String\", \"CONSTANT_Fieldref\", \"CONSTANT_Methodref\", \"CONSTANT_InterfaceMethodref\", \"CONSTANT_NameAndType\" }"
STATIC_INITIALIZER_NAME = "String  \"<clinit>\""
CONSTRUCTOR_NAME = "String  \"<init>\""
INTERFACES_IMPLEMENTED_BY_ARRAYS = "String[]  { \"java.lang.Cloneable\", \"java.io.Serializable\" }"
MAX_CP_ENTRIES = "int  65535"
MAX_CODE_SIZE = "int  65536"
NOP = "short  0"
ACONST_NULL = "short  1"
ICONST_M1 = "short  2"
ICONST_0 = "short  3"
ICONST_1 = "short  4"
ICONST_2 = "short  5"
ICONST_3 = "short  6"
ICONST_4 = "short  7"
ICONST_5 = "short  8"
LCONST_0 = "short  9"
LCONST_1 = "short  10"
FCONST_0 = "short  11"
FCONST_1 = "short  12"
FCONST_2 = "short  13"
DCONST_0 = "short  14"
DCONST_1 = "short  15"
BIPUSH = "short  16"
SIPUSH = "short  17"
LDC = "short  18"
LDC_W = "short  19"
LDC2_W = "short  20"
ILOAD = "short  21"
LLOAD = "short  22"
FLOAD = "short  23"
DLOAD = "short  24"
ALOAD = "short  25"
ILOAD_0 = "short  26"
ILOAD_1 = "short  27"
ILOAD_2 = "short  28"
ILOAD_3 = "short  29"
LLOAD_0 = "short  30"
LLOAD_1 = "short  31"
LLOAD_2 = "short  32"
LLOAD_3 = "short  33"
FLOAD_0 = "short  34"
FLOAD_1 = "short  35"
FLOAD_2 = "short  36"
FLOAD_3 = "short  37"
DLOAD_0 = "short  38"
DLOAD_1 = "short  39"
DLOAD_2 = "short  40"
DLOAD_3 = "short  41"
ALOAD_0 = "short  42"
ALOAD_1 = "short  43"
ALOAD_2 = "short  44"
ALOAD_3 = "short  45"
IALOAD = "short  46"
LALOAD = "short  47"
FALOAD = "short  48"
DALOAD = "short  49"
AALOAD = "short  50"
BALOAD = "short  51"
CALOAD = "short  52"
SALOAD = "short  53"
ISTORE = "short  54"
LSTORE = "short  55"
FSTORE = "short  56"
DSTORE = "short  57"
ASTORE = "short  58"
ISTORE_0 = "short  59"
ISTORE_1 = "short  60"
ISTORE_2 = "short  61"
ISTORE_3 = "short  62"
LSTORE_0 = "short  63"
LSTORE_1 = "short  64"
LSTORE_2 = "short  65"
LSTORE_3 = "short  66"
FSTORE_0 = "short  67"
FSTORE_1 = "short  68"
FSTORE_2 = "short  69"
FSTORE_3 = "short  70"
DSTORE_0 = "short  71"
DSTORE_1 = "short  72"
DSTORE_2 = "short  73"
DSTORE_3 = "short  74"
ASTORE_0 = "short  75"
ASTORE_1 = "short  76"
ASTORE_2 = "short  77"
ASTORE_3 = "short  78"
IASTORE = "short  79"
LASTORE = "short  80"
FASTORE = "short  81"
DASTORE = "short  82"
AASTORE = "short  83"
BASTORE = "short  84"
CASTORE = "short  85"
SASTORE = "short  86"
POP = "short  87"
POP2 = "short  88"
DUP = "short  89"
DUP_X1 = "short  90"
DUP_X2 = "short  91"
DUP2 = "short  92"
DUP2_X1 = "short  93"
DUP2_X2 = "short  94"
SWAP = "short  95"
IADD = "short  96"
LADD = "short  97"
FADD = "short  98"
DADD = "short  99"
ISUB = "short  100"
LSUB = "short  101"
FSUB = "short  102"
DSUB = "short  103"
IMUL = "short  104"
LMUL = "short  105"
FMUL = "short  106"
DMUL = "short  107"
IDIV = "short  108"
LDIV = "short  109"
FDIV = "short  110"
DDIV = "short  111"
IREM = "short  112"
LREM = "short  113"
FREM = "short  114"
DREM = "short  115"
INEG = "short  116"
LNEG = "short  117"
FNEG = "short  118"
DNEG = "short  119"
ISHL = "short  120"
LSHL = "short  121"
ISHR = "short  122"
LSHR = "short  123"
IUSHR = "short  124"
LUSHR = "short  125"
IAND = "short  126"
LAND = "short  127"
IOR = "short  128"
LOR = "short  129"
IXOR = "short  130"
LXOR = "short  131"
IINC = "short  132"
I2L = "short  133"
I2F = "short  134"
I2D = "short  135"
L2I = "short  136"
L2F = "short  137"
L2D = "short  138"
F2I = "short  139"
F2L = "short  140"
F2D = "short  141"
D2I = "short  142"
D2L = "short  143"
D2F = "short  144"
I2B = "short  145"
INT2BYTE = "short  145"
I2C = "short  146"
INT2CHAR = "short  146"
I2S = "short  147"
INT2SHORT = "short  147"
LCMP = "short  148"
FCMPL = "short  149"
FCMPG = "short  150"
DCMPL = "short  151"
DCMPG = "short  152"
IFEQ = "short  153"
IFNE = "short  154"
IFLT = "short  155"
IFGE = "short  156"
IFGT = "short  157"
IFLE = "short  158"
IF_ICMPEQ = "short  159"
IF_ICMPNE = "short  160"
IF_ICMPLT = "short  161"
IF_ICMPGE = "short  162"
IF_ICMPGT = "short  163"
IF_ICMPLE = "short  164"
IF_ACMPEQ = "short  165"
IF_ACMPNE = "short  166"
GOTO = "short  167"
JSR = "short  168"
RET = "short  169"
TABLESWITCH = "short  170"
LOOKUPSWITCH = "short  171"
IRETURN = "short  172"
LRETURN = "short  173"
FRETURN = "short  174"
DRETURN = "short  175"
ARETURN = "short  176"
RETURN = "short  177"
GETSTATIC = "short  178"
PUTSTATIC = "short  179"
GETFIELD = "short  180"
PUTFIELD = "short  181"
INVOKEVIRTUAL = "short  182"
INVOKESPECIAL = "short  183"
INVOKENONVIRTUAL = "short  183"
INVOKESTATIC = "short  184"
INVOKEINTERFACE = "short  185"
NEW = "short  187"
NEWARRAY = "short  188"
ANEWARRAY = "short  189"
ARRAYLENGTH = "short  190"
ATHROW = "short  191"
CHECKCAST = "short  192"
INSTANCEOF = "short  193"
MONITORENTER = "short  194"
MONITOREXIT = "short  195"
WIDE = "short  196"
MULTIANEWARRAY = "short  197"
IFNULL = "short  198"
IFNONNULL = "short  199"
GOTO_W = "short  200"
JSR_W = "short  201"
BREAKPOINT = "short  202"
LDC_QUICK = "short  203"
LDC_W_QUICK = "short  204"
LDC2_W_QUICK = "short  205"
GETFIELD_QUICK = "short  206"
PUTFIELD_QUICK = "short  207"
GETFIELD2_QUICK = "short  208"
PUTFIELD2_QUICK = "short  209"
GETSTATIC_QUICK = "short  210"
PUTSTATIC_QUICK = "short  211"
GETSTATIC2_QUICK = "short  212"
PUTSTATIC2_QUICK = "short  213"
INVOKEVIRTUAL_QUICK = "short  214"
INVOKENONVIRTUAL_QUICK = "short  215"
INVOKESUPER_QUICK = "short  216"
INVOKESTATIC_QUICK = "short  217"
INVOKEINTERFACE_QUICK = "short  218"
INVOKEVIRTUALOBJECT_QUICK = "short  219"
NEW_QUICK = "short  221"
ANEWARRAY_QUICK = "short  222"
MULTIANEWARRAY_QUICK = "short  223"
CHECKCAST_QUICK = "short  224"
INSTANCEOF_QUICK = "short  225"
INVOKEVIRTUAL_QUICK_W = "short  226"
GETFIELD_QUICK_W = "short  227"
PUTFIELD_QUICK_W = "short  228"
IMPDEP1 = "short  254"
IMPDEP2 = "short  255"
PUSH = "short  4711"
SWITCH = "short  4712"
UNDEFINED = "short  -1"
UNPREDICTABLE = "short  -2"
RESERVED = "short  -3"
ILLEGAL_OPCODE = "String  \"<illegal opcode>\""
ILLEGAL_TYPE = "String  \"<illegal type>\""
T_BOOLEAN = "byte  4"
T_CHAR = "byte  5"
T_FLOAT = "byte  6"
T_DOUBLE = "byte  7"
T_BYTE = "byte  8"
T_SHORT = "byte  9"
T_INT = "byte  10"
T_LONG = "byte  11"
T_VOID = "byte  12"
T_ARRAY = "byte  13"
T_OBJECT = "byte  14"
T_REFERENCE = "byte  14"
T_UNKNOWN = "byte  15"
T_ADDRESS = "byte  16"
TYPE_NAMES = "String[]  { \"<illegal type>\", \"<illegal type>\", \"<illegal type>\", \"<illegal type>\", \"boolean\", \"char\", \"float\", \"double\", \"byte\", \"short\", \"int\", \"long\", \"void\", \"array\", \"object\", \"unknown\" }"
CLASS_TYPE_NAMES = "String[]  { \"<illegal type>\", \"<illegal type>\", \"<illegal type>\", \"<illegal type>\", \"java.lang.Boolean\", \"java.lang.Character\", \"java.lang.Float\", \"java.lang.Double\", \"java.lang.Byte\", \"java.lang.Short\", \"java.lang.Integer\", \"java.lang.Long\", \"java.lang.Void\", \"<illegal type>\", \"<illegal type>\", \"<illegal type>\" }"
SHORT_TYPE_NAMES = "String[]  { \"<illegal type>\", \"<illegal type>\", \"<illegal type>\", \"<illegal type>\", \"Z\", \"C\", \"F\", \"D\", \"B\", \"S\", \"I\", \"J\", \"V\", \"<illegal type>\", \"<illegal type>\", \"<illegal type>\" }"
NO_OF_OPERANDS = "short[]  { 0, 0, 0, 0, 0, 0, 0, 0, 0, 0, 0, 0, 0, 0, 0, 0, 1, 2, 1, 2, 2, 1, 1, 1, 1, 1, 0, 0, 0, 0, 0, 0, 0, 0, 0, 0, 0, 0, 0, 0, 0, 0, 0, 0, 0, 0, 0, 0, 0, 0, 0, 0, 0, 0, 1, 1, 1, 1, 1, 0, 0, 0, 0, 0, 0, 0, 0, 0, 0, 0, 0, 0, 0, 0, 0, 0, 0, 0, 0, 0, 0, 0, 0, 0, 0, 0, 0, 0, 0, 0, 0, 0, 0, 0, 0, 0, 0, 0, 0, 0, 0, 0, 0, 0, 0, 0, 0, 0, 0, 0, 0, 0, 0, 0, 0, 0, 0, 0, 0, 0, 0, 0, 0, 0, 0, 0, 0, 0, 0, 0, 0, 0, 2, 0, 0, 0, 0, 0, 0, 0, 0, 0, 0, 0, 0, 0, 0, 0, 0, 0, 0, 0, 0, 2, 2, 2, 2, 2, 2, 2, 2, 2, 2, 2, 2, 2, 2, 2, 2, 1, -2, -2, 0, 0, 0, 0, 0, 0, 2, 2, 2, 2, 2, 2, 2, 4, -1, 2, 1, 2, 0, 0, 2, 2, 0, 0, -2, 3, 2, 2, 4, 4, 0, -1, -1, -1, -1, -1, -1, -1, -1, -1, -1, -1, -1, -1, -1, -1, -1, -1, -1, -1, -1, -1, -1, -1, -1, -1, -1, -1, -1, -1, -1, -1, -1, -1, -1, -1, -1, -1, -1, -1, -1, -1, -1, -1, -1, -1, -1, -1, -1, -1, -1, -1, -3, -3 }"
TYPE_OF_OPERANDS = "short[][]  { new short[0], new short[0], new short[0], new short[0], new short[0], new short[0], new short[0], new short[0], new short[0], new short[0], new short[0], new short[0], new short[0], new short[0], new short[0], new short[0], { 8 }, { 9 }, { 8 }, { 9 }, { 9 }, { 8 }, { 8 }, { 8 }, { 8 }, { 8 }, new short[0], new short[0], new short[0], new short[0], new short[0], new short[0], new short[0], new short[0], new short[0], new short[0], new short[0], new short[0], new short[0], new short[0], new short[0], new short[0], new short[0], new short[0], new short[0], new short[0], new short[0], new short[0], new short[0], new short[0], new short[0], new short[0], new short[0], new short[0], { 8 }, { 8 }, { 8 }, { 8 }, { 8 }, new short[0], new short[0], new short[0], new short[0], new short[0], new short[0], new short[0], new short[0], new short[0], new short[0], new short[0], new short[0], new short[0], new short[0], new short[0], new short[0], new short[0], new short[0], new short[0], new short[0], new short[0], new short[0], new short[0], new short[0], new short[0], new short[0], new short[0], new short[0], new short[0], new short[0], new short[0], new short[0], new short[0], new short[0], new short[0], new short[0], new short[0], new short[0], new short[0], new short[0], new short[0], new short[0], new short[0], new short[0], new short[0], new short[0], new short[0], new short[0], new short[0], new short[0], new short[0], new short[0], new short[0], new short[0], new short[0], new short[0], new short[0], new short[0], new short[0], new short[0], new short[0], new short[0], new short[0], new short[0], new short[0], new short[0], new short[0], new short[0], new short[0], new short[0], new short[0], new short[0], new short[0], { 8, 8 }, new short[0], new short[0], new short[0], new short[0], new short[0], new short[0], new short[0], new short[0], new short[0], new short[0], new short[0], new short[0], new short[0], new short[0], new short[0], new short[0], new short[0], new short[0], new short[0], new short[0], { 9 }, { 9 }, { 9 }, { 9 }, { 9 }, { 9 }, { 9 }, { 9 }, { 9 }, { 9 }, { 9 }, { 9 }, { 9 }, { 9 }, { 9 }, { 9 }, { 8 }, new short[0], new short[0], new short[0], new short[0], new short[0], new short[0], new short[0], new short[0], { 9 }, { 9 }, { 9 }, { 9 }, { 9 }, { 9 }, { 9 }, { 9, 8, 8 }, new short[0], { 9 }, { 8 }, { 9 }, new short[0], new short[0], { 9 }, { 9 }, new short[0], new short[0], { 8 }, { 9, 8 }, { 9 }, { 9 }, { 10 }, { 10 }, new short[0], new short[0], new short[0], new short[0], new short[0], new short[0], new short[0], new short[0], new short[0], new short[0], new short[0], new short[0], new short[0], new short[0], new short[0], new short[0], new short[0], new short[0], new short[0], new short[0], new short[0], new short[0], new short[0], new short[0], new short[0], new short[0], new short[0], new short[0], new short[0], new short[0], new short[0], new short[0], new short[0], new short[0], new short[0], new short[0], new short[0], new short[0], new short[0], new short[0], new short[0], new short[0], new short[0], new short[0], new short[0], new short[0], new short[0], new short[0], new short[0], new short[0], new short[0], new short[0], new short[0], new short[0] }"
OPCODE_NAMES = "String[]  { \"nop\", \"aconst_null\", \"iconst_m1\", \"iconst_0\", \"iconst_1\", \"iconst_2\", \"iconst_3\", \"iconst_4\", \"iconst_5\", \"lconst_0\", \"lconst_1\", \"fconst_0\", \"fconst_1\", \"fconst_2\", \"dconst_0\", \"dconst_1\", \"bipush\", \"sipush\", \"ldc\", \"ldc_w\", \"ldc2_w\", \"iload\", \"lload\", \"fload\", \"dload\", \"aload\", \"iload_0\", \"iload_1\", \"iload_2\", \"iload_3\", \"lload_0\", \"lload_1\", \"lload_2\", \"lload_3\", \"fload_0\", \"fload_1\", \"fload_2\", \"fload_3\", \"dload_0\", \"dload_1\", \"dload_2\", \"dload_3\", \"aload_0\", \"aload_1\", \"aload_2\", \"aload_3\", \"iaload\", \"laload\", \"faload\", \"daload\", \"aaload\", \"baload\", \"caload\", \"saload\", \"istore\", \"lstore\", \"fstore\", \"dstore\", \"astore\", \"istore_0\", \"istore_1\", \"istore_2\", \"istore_3\", \"lstore_0\", \"lstore_1\", \"lstore_2\", \"lstore_3\", \"fstore_0\", \"fstore_1\", \"fstore_2\", \"fstore_3\", \"dstore_0\", \"dstore_1\", \"dstore_2\", \"dstore_3\", \"astore_0\", \"astore_1\", \"astore_2\", \"astore_3\", \"iastore\", \"lastore\", \"fastore\", \"dastore\", \"aastore\", \"bastore\", \"castore\", \"sastore\", \"pop\", \"pop2\", \"dup\", \"dup_x1\", \"dup_x2\", \"dup2\", \"dup2_x1\", \"dup2_x2\", \"swap\", \"iadd\", \"ladd\", \"fadd\", \"dadd\", \"isub\", \"lsub\", \"fsub\", \"dsub\", \"imul\", \"lmul\", \"fmul\", \"dmul\", \"idiv\", \"ldiv\", \"fdiv\", \"ddiv\", \"irem\", \"lrem\", \"frem\", \"drem\", \"ineg\", \"lneg\", \"fneg\", \"dneg\", \"ishl\", \"lshl\", \"ishr\", \"lshr\", \"iushr\", \"lushr\", \"iand\", \"land\", \"ior\", \"lor\", \"ixor\", \"lxor\", \"iinc\", \"i2l\", \"i2f\", \"i2d\", \"l2i\", \"l2f\", \"l2d\", \"f2i\", \"f2l\", \"f2d\", \"d2i\", \"d2l\", \"d2f\", \"i2b\", \"i2c\", \"i2s\", \"lcmp\", \"fcmpl\", \"fcmpg\", \"dcmpl\", \"dcmpg\", \"ifeq\", \"ifne\", \"iflt\", \"ifge\", \"ifgt\", \"ifle\", \"if_icmpeq\", \"if_icmpne\", \"if_icmplt\", \"if_icmpge\", \"if_icmpgt\", \"if_icmple\", \"if_acmpeq\", \"if_acmpne\", \"goto\", \"jsr\", \"ret\", \"tableswitch\", \"lookupswitch\", \"ireturn\", \"lreturn\", \"freturn\", \"dreturn\", \"areturn\", \"return\", \"getstatic\", \"putstatic\", \"getfield\", \"putfield\", \"invokevirtual\", \"invokespecial\", \"invokestatic\", \"invokeinterface\", \"<illegal opcode>\", \"new\", \"newarray\", \"anewarray\", \"arraylength\", \"athrow\", \"checkcast\", \"instanceof\", \"monitorenter\", \"monitorexit\", \"wide\", \"multianewarray\", \"ifnull\", \"ifnonnull\", \"goto_w\", \"jsr_w\", \"breakpoint\", \"<illegal opcode>\", \"<illegal opcode>\", \"<illegal opcode>\", \"<illegal opcode>\", \"<illegal opcode>\", \"<illegal opcode>\", \"<illegal opcode>\", \"<illegal opcode>\", \"<illegal opcode>\", \"<illegal opcode>\", \"<illegal opcode>\", \"<illegal opcode>\", \"<illegal opcode>\", \"<illegal opcode>\", \"<illegal opcode>\", \"<illegal opcode>\", \"<illegal opcode>\", \"<illegal opcode>\", \"<illegal opcode>\", \"<illegal opcode>\", \"<illegal opcode>\", \"<illegal opcode>\", \"<illegal opcode>\", \"<illegal opcode>\", \"<illegal opcode>\", \"<illegal opcode>\", \"<illegal opcode>\", \"<illegal opcode>\", \"<illegal opcode>\", \"<illegal opcode>\", \"<illegal opcode>\", \"<illegal opcode>\", \"<illegal opcode>\", \"<illegal opcode>\", \"<illegal opcode>\", \"<illegal opcode>\", \"<illegal opcode>\", \"<illegal opcode>\", \"<illegal opcode>\", \"<illegal opcode>\", \"<illegal opcode>\", \"<illegal opcode>\", \"<illegal opcode>\", \"<illegal opcode>\", \"<illegal opcode>\", \"<illegal opcode>\", \"<illegal opcode>\", \"<illegal opcode>\", \"<illegal opcode>\", \"<illegal opcode>\", \"<illegal opcode>\", \"impdep1\", \"impdep2\" }"
CONSUME_STACK = "int[]  { 0, 0, 0, 0, 0, 0, 0, 0, 0, 0, 0, 0, 0, 0, 0, 0, 0, 0, 0, 0, 0, 0, 0, 0, 0, 0, 0, 0, 0, 0, 0, 0, 0, 0, 0, 0, 0, 0, 0, 0, 0, 0, 0, 0, 0, 0, 2, 2, 2, 2, 2, 2, 2, 2, 1, 2, 1, 2, 1, 1, 1, 1, 1, 2, 2, 2, 2, 1, 1, 1, 1, 2, 2, 2, 2, 1, 1, 1, 1, 3, 4, 3, 4, 3, 3, 3, 3, 1, 2, 1, 2, 3, 2, 3, 4, 2, 2, 4, 2, 4, 2, 4, 2, 4, 2, 4, 2, 4, 2, 4, 2, 4, 2, 4, 2, 4, 1, 2, 1, 2, 2, 3, 2, 3, 2, 3, 2, 4, 2, 4, 2, 4, 0, 1, 1, 1, 2, 2, 2, 1, 1, 1, 2, 2, 2, 1, 1, 1, 4, 2, 2, 4, 4, 1, 1, 1, 1, 1, 1, 2, 2, 2, 2, 2, 2, 2, 2, 0, 0, 0, 1, 1, 1, 2, 1, 2, 1, 0, 0, -2, 1, -2, -2, -2, -2, -2, -1, 0, 1, 1, 1, 1, 1, 1, 1, 1, 0, -2, 1, 1, 0, 0, 0, -1, -1, -1, -1, -1, -1, -1, -1, -1, -1, -1, -1, -1, -1, -1, -1, -1, -1, -1, -1, -1, -1, -1, -1, -1, -1, -1, -1, -1, -1, -1, -1, -1, -1, -1, -1, -1, -1, -1, -1, -1, -1, -1, -1, -1, -1, -1, -1, -1, -1, -1, -2, -2 }"
PRODUCE_STACK = "int[]  { 0, 1, 1, 1, 1, 1, 1, 1, 1, 2, 2, 1, 1, 1, 2, 2, 1, 1, 1, 1, 2, 1, 2, 1, 2, 1, 1, 1, 1, 1, 2, 2, 2, 2, 1, 1, 1, 1, 2, 2, 2, 2, 1, 1, 1, 1, 1, 2, 1, 2, 1, 1, 1, 1, 0, 0, 0, 0, 0, 0, 0, 0, 0, 0, 0, 0, 0, 0, 0, 0, 0, 0, 0, 0, 0, 0, 0, 0, 0, 0, 0, 0, 0, 0, 0, 0, 0, 0, 0, 2, 3, 4, 4, 5, 6, 2, 1, 2, 1, 2, 1, 2, 1, 2, 1, 2, 1, 2, 1, 2, 1, 2, 1, 2, 1, 2, 1, 2, 1, 2, 1, 2, 1, 2, 1, 2, 1, 2, 1, 2, 1, 2, 0, 2, 1, 2, 1, 1, 2, 1, 2, 2, 1, 2, 1, 1, 1, 1, 1, 1, 1, 1, 1, 0, 0, 0, 0, 0, 0, 0, 0, 0, 0, 0, 0, 0, 0, 0, 1, 0, 0, 0, 0, 0, 0, 0, 0, 0, -2, 0, -2, 0, -2, -2, -2, -2, -1, 1, 1, 1, 1, 1, 1, 1, 0, 0, 0, 1, 0, 0, 0, 1, 0, -1, -1, -1, -1, -1, -1, -1, -1, -1, -1, -1, -1, -1, -1, -1, -1, -1, -1, -1, -1, -1, -1, -1, -1, -1, -1, -1, -1, -1, -1, -1, -1, -1, -1, -1, -1, -1, -1, -1, -1, -1, -1, -1, -1, -1, -1, -1, -1, -1, -1, -1, -2, -2 }"
ATTR_UNKNOWN = "byte  -1"
ATTR_SOURCE_FILE = "byte  0"
ATTR_CONSTANT_VALUE = "byte  1"
ATTR_CODE = "byte  2"
ATTR_EXCEPTIONS = "byte  3"
ATTR_LINE_NUMBER_TABLE = "byte  4"
ATTR_LOCAL_VARIABLE_TABLE = "byte  5"
ATTR_INNER_CLASSES = "byte  6"
ATTR_SYNTHETIC = "byte  7"
ATTR_DEPRECATED = "byte  8"
ATTR_PMG = "byte  9"
ATTR_SIGNATURE = "byte  10"
ATTR_STACK_MAP = "byte  11"
ATTR_RUNTIMEVISIBLE_ANNOTATIONS = "byte  12"
ATTR_RUNTIMEINVISIBLE_ANNOTATIONS = "byte  13"
ATTR_RUNTIMEVISIBLE_PARAMETER_ANNOTATIONS = "byte  14"
ATTR_RUNTIMEINVISIBLE_PARAMETER_ANNOTATIONS = "byte  15"
ATTR_ANNOTATION_DEFAULT = "byte  16"
KNOWN_ATTRIBUTES = "short  12"
ATTRIBUTE_NAMES = "String[]  { \"SourceFile\", \"ConstantValue\", \"Code\", \"Exceptions\", \"LineNumberTable\", \"LocalVariableTable\", \"InnerClasses\", \"Synthetic\", \"Deprecated\", \"PMGClass\", \"Signature\", \"StackMap\", \"RuntimeVisibleAnnotations\", \"RuntimeInvisibleAnnotations\", \"RuntimeVisibleParameterAnnotations\", \"RuntimeInvisibleParameterAnnotations\", \"AnnotationDefault\" }"
ITEM_Bogus = "byte  0"
ITEM_Integer = "byte  1"
ITEM_Float = "byte  2"
ITEM_Double = "byte  3"
ITEM_Long = "byte  4"
ITEM_Null = "byte  5"
ITEM_InitObject = "byte  6"
ITEM_Object = "byte  7"
ITEM_NewObject = "byte  8"
ITEM_NAMES = "String[]  { \"Bogus\", \"Integer\", \"Float\", \"Double\", \"Long\", \"Null\", \"InitObject\", \"Object\", \"NewObject\" }"
