ASM4 = "int  262144"
V1_1 = "int  196653"
V1_2 = "int  46"
V1_3 = "int  47"
V1_4 = "int  48"
V1_5 = "int  49"
V1_6 = "int  50"
V1_7 = "int  51"
ACC_PUBLIC = "int  1"
ACC_PRIVATE = "int  2"
ACC_PROTECTED = "int  4"
ACC_STATIC = "int  8"
ACC_FINAL = "int  16"
ACC_SUPER = "int  32"
ACC_SYNCHRONIZED = "int  32"
ACC_VOLATILE = "int  64"
ACC_BRIDGE = "int  64"
ACC_VARARGS = "int  128"
ACC_TRANSIENT = "int  128"
ACC_NATIVE = "int  256"
ACC_INTERFACE = "int  512"
ACC_ABSTRACT = "int  1024"
ACC_STRICT = "int  2048"
ACC_SYNTHETIC = "int  4096"
ACC_ANNOTATION = "int  8192"
ACC_ENUM = "int  16384"
ACC_DEPRECATED = "int  131072"
T_BOOLEAN = "int  4"
T_CHAR = "int  5"
T_FLOAT = "int  6"
T_DOUBLE = "int  7"
T_BYTE = "int  8"
T_SHORT = "int  9"
T_INT = "int  10"
T_LONG = "int  11"
H_GETFIELD = "int  1"
H_GETSTATIC = "int  2"
H_PUTFIELD = "int  3"
H_PUTSTATIC = "int  4"
H_INVOKEVIRTUAL = "int  5"
H_INVOKESTATIC = "int  6"
H_INVOKESPECIAL = "int  7"
H_NEWINVOKESPECIAL = "int  8"
H_INVOKEINTERFACE = "int  9"
F_NEW = "int  -1"
F_FULL = "int  0"
F_APPEND = "int  1"
F_CHOP = "int  2"
F_SAME = "int  3"
F_SAME1 = "int  4"
TOP = "Integer  new Integer(0)"
INTEGER = "Integer  new Integer(1)"
FLOAT = "Integer  new Integer(2)"
DOUBLE = "Integer  new Integer(3)"
LONG = "Integer  new Integer(4)"
NULL = "Integer  new Integer(5)"
UNINITIALIZED_THIS = "Integer  new Integer(6)"
NOP = "int  0"
ACONST_NULL = "int  1"
ICONST_M1 = "int  2"
ICONST_0 = "int  3"
ICONST_1 = "int  4"
ICONST_2 = "int  5"
ICONST_3 = "int  6"
ICONST_4 = "int  7"
ICONST_5 = "int  8"
LCONST_0 = "int  9"
LCONST_1 = "int  10"
FCONST_0 = "int  11"
FCONST_1 = "int  12"
FCONST_2 = "int  13"
DCONST_0 = "int  14"
DCONST_1 = "int  15"
BIPUSH = "int  16"
SIPUSH = "int  17"
LDC = "int  18"
ILOAD = "int  21"
LLOAD = "int  22"
FLOAD = "int  23"
DLOAD = "int  24"
ALOAD = "int  25"
IALOAD = "int  46"
LALOAD = "int  47"
FALOAD = "int  48"
DALOAD = "int  49"
AALOAD = "int  50"
BALOAD = "int  51"
CALOAD = "int  52"
SALOAD = "int  53"
ISTORE = "int  54"
LSTORE = "int  55"
FSTORE = "int  56"
DSTORE = "int  57"
ASTORE = "int  58"
IASTORE = "int  79"
LASTORE = "int  80"
FASTORE = "int  81"
DASTORE = "int  82"
AASTORE = "int  83"
BASTORE = "int  84"
CASTORE = "int  85"
SASTORE = "int  86"
POP = "int  87"
POP2 = "int  88"
DUP = "int  89"
DUP_X1 = "int  90"
DUP_X2 = "int  91"
DUP2 = "int  92"
DUP2_X1 = "int  93"
DUP2_X2 = "int  94"
SWAP = "int  95"
IADD = "int  96"
LADD = "int  97"
FADD = "int  98"
DADD = "int  99"
ISUB = "int  100"
LSUB = "int  101"
FSUB = "int  102"
DSUB = "int  103"
IMUL = "int  104"
LMUL = "int  105"
FMUL = "int  106"
DMUL = "int  107"
IDIV = "int  108"
LDIV = "int  109"
FDIV = "int  110"
DDIV = "int  111"
IREM = "int  112"
LREM = "int  113"
FREM = "int  114"
DREM = "int  115"
INEG = "int  116"
LNEG = "int  117"
FNEG = "int  118"
DNEG = "int  119"
ISHL = "int  120"
LSHL = "int  121"
ISHR = "int  122"
LSHR = "int  123"
IUSHR = "int  124"
LUSHR = "int  125"
IAND = "int  126"
LAND = "int  127"
IOR = "int  128"
LOR = "int  129"
IXOR = "int  130"
LXOR = "int  131"
IINC = "int  132"
I2L = "int  133"
I2F = "int  134"
I2D = "int  135"
L2I = "int  136"
L2F = "int  137"
L2D = "int  138"
F2I = "int  139"
F2L = "int  140"
F2D = "int  141"
D2I = "int  142"
D2L = "int  143"
D2F = "int  144"
I2B = "int  145"
I2C = "int  146"
I2S = "int  147"
LCMP = "int  148"
FCMPL = "int  149"
FCMPG = "int  150"
DCMPL = "int  151"
DCMPG = "int  152"
IFEQ = "int  153"
IFNE = "int  154"
IFLT = "int  155"
IFGE = "int  156"
IFGT = "int  157"
IFLE = "int  158"
IF_ICMPEQ = "int  159"
IF_ICMPNE = "int  160"
IF_ICMPLT = "int  161"
IF_ICMPGE = "int  162"
IF_ICMPGT = "int  163"
IF_ICMPLE = "int  164"
IF_ACMPEQ = "int  165"
IF_ACMPNE = "int  166"
GOTO = "int  167"
JSR = "int  168"
RET = "int  169"
TABLESWITCH = "int  170"
LOOKUPSWITCH = "int  171"
IRETURN = "int  172"
LRETURN = "int  173"
FRETURN = "int  174"
DRETURN = "int  175"
ARETURN = "int  176"
RETURN = "int  177"
GETSTATIC = "int  178"
PUTSTATIC = "int  179"
GETFIELD = "int  180"
PUTFIELD = "int  181"
INVOKEVIRTUAL = "int  182"
INVOKESPECIAL = "int  183"
INVOKESTATIC = "int  184"
INVOKEINTERFACE = "int  185"
INVOKEDYNAMIC = "int  186"
NEW = "int  187"
NEWARRAY = "int  188"
ANEWARRAY = "int  189"
ARRAYLENGTH = "int  190"
ATHROW = "int  191"
CHECKCAST = "int  192"
INSTANCEOF = "int  193"
MONITORENTER = "int  194"
MONITOREXIT = "int  195"
MULTIANEWARRAY = "int  197"
IFNULL = "int  198"
IFNONNULL = "int  199"
